coercion.py
coercion-1.0.0.dist-info/zip-safe
coercion-1.0.0.dist-info/top_level.txt
coercion-1.0.0.dist-info/METADATA
coercion-1.0.0.dist-info/DESCRIPTION.rst
coercion-1.0.0.dist-info/metadata.json
coercion-1.0.0.dist-info/WHEEL
coercion-1.0.0.dist-info/RECORD
