Metadata-Version: 2.0
Name: coercion
Version: 1.0.0
Summary: Coercing data into a normalized form
Home-page: https://github.com/dave-shawley/coercion
Author: Dave Shawley
Author-email: daveshawley@gmail.com
License: BSD
Platform: any
Classifier: Intended Audience :: Developers
Classifier: License :: OSI Approved :: BSD License
Classifier: Operating System :: OS Independent
Classifier: Programming Language :: Python
Classifier: Programming Language :: Python :: 2
Classifier: Programming Language :: Python :: 3
Classifier: Development Status :: 1 - Planning
Classifier: Topic :: Text Processing
